{
    "characters": [
        {
            "id": "000101",
            "character": "Lathel",
            "costume": "Medicinal Herb Tracker",
            "character_image": "illust_inven_char000101_1.png",
            "skill_preview_image": "illust_skill_char000101_1.png",
            "standing": {
                "skeleton": "char000101.skel",
                "atlas": "char000101.atlas"
            },
            "cutscene": {
                "skeleton": "cutscene_char000101.skel",
                "atlas": "cutscene_char000101.atlas"
            },
            "dating": null
        },
        {
            "id": "000102",
            "character": "Lathel",
            "costume": "Lonely Survivor",
            "character_image": "illust_inven_char000102_44.png",
            "skill_preview_image": "illust_skill_char000102_44.png",
            "standing": {
                "skeleton": "char000102.skel",
                "atlas": "char000102.atlas"
            },
            "cutscene": null,
            "dating": null
        },
        {
            "id": "000103",
            "character": "Lathel",
            "costume": "Homunculus",
            "character_image": "illust_inven_char000103_59.png",
            "skill_preview_image": "illust_skill_char000103_59.png",
            "standing": {
                "skeleton": "char000103.skel",
                "atlas": "char000103.atlas"
            },
            "cutscene": {
                "skeleton": "cutscene_char000103.skel",
                "atlas": "cutscene_char000103.atlas"
            },
            "dating": null
        },
        {
            "id": "000104",
            "character": "Lathel",
            "costume": "Dark Knight",
            "character_image": "illust_inven_char000104_69.png",
            "skill_preview_image": "illust_skill_char000104_69.png",
            "standing": {
                "skeleton": "char000104.skel",
                "atlas": "char000104.atlas"
            },
            "cutscene": null,
            "dating": null
        },
        {
            "id": "000105",
            "character": "Lathel",
            "costume": "Promise of Vengance",
            "character_image": "illust_inven_char000105_42.png",
            "skill_preview_image": "illust_skill_char000105_42.png",
            "standing": {
                "skeleton": "char000105.skel",
                "atlas": "char000105.atlas"
            },
            "cutscene": null,
            "dating": null
        },
        {
            "id": "000106",
            "character": "Lathel",
            "costume": "Pool Party",
            "character_image": "illust_inven_char000106_90.png",
            "skill_preview_image": "illust_skill_char000106_90.png",
            "standing": {
                "skeleton": "char000106.skel",
                "atlas": "char000106.atlas"
            },
            "cutscene": null,
            "dating": null
        },
        {
            "id": "000201",
            "character": "Justia",
            "costume": "Knight of Blood",
            "character_image": "illust_inven_char000201_2.png",
            "skill_preview_image": "illust_skill_char000201_2.png",
            "standing": {
                "skeleton": "char000201.skel",
                "atlas": "char000201.atlas"
            },
            "cutscene": null,
            "dating": null
        },
        {
            "id": "000202",
            "character": "Justia",
            "costume": "White Reaper",
            "character_image": "illust_inven_char000202_3.png",
            "skill_preview_image": "illust_skill_char000202_3.png",
            "standing": {
                "skeleton": "char000202.skel",
                "atlas": "char000202.atlas"
            },
            "cutscene": {
                "skeleton": "cutscene_char000202.skel",
                "atlas": "cutscene_char000202.atlas"
            },
            "dating": null
        },
        {
            "id": "000203",
            "character": "Justia",
            "costume": "Blood Glutton",
            "character_image": "illust_inven_char000203_41.png",
            "skill_preview_image": "illust_skill_char000203_41.png",
            "standing": {
                "skeleton": "char000203.skel",
                "atlas": "char000203.atlas"
            },
            "cutscene": {
                "skeleton": "CutScene_Char000203.skel",
                "atlas": "CutScene_Char000203.atlas"
            },
            "dating": null
        },
        {
            "id": "000204",
            "character": "Justia",
            "costume": "Kendo Club",
            "character_image": "illust_inven_char000204_15.png",
            "skill_preview_image": "illust_skill_char000204_15.png",
            "standing": {
                "skeleton": "char000204.skel",
                "atlas": "char000204.atlas"
            },
            "cutscene": {
                "skeleton": "cutscene_char000204.skel",
                "atlas": "cutscene_char000204.atlas"
            },
            "dating": null
        },
        {
            "id": "000206",
            "character": "Justia",
            "costume": "Pool Party",
            "character_image": "illust_inven_char000206_91.png",
            "skill_preview_image": "illust_skill_char000206_91.png",
            "standing": {
                "skeleton": "char000206.skel",
                "atlas": "char000206.atlas"
            },
            "cutscene": {
                "skeleton": "cutscene_char000206.skel",
                "atlas": "cutscene_char000206.atlas"
            },
            "dating": null
        },
        {
            "id": "000296",
            "character": "Justia",
            "costume": "Hot Summer Dream",
            "character_image": "illust_inven_char000296_174.png",
            "skill_preview_image": "illust_skill_char000296_174.png",
            "standing": {
                "skeleton": "char000296.skel",
                "atlas": "char000296.atlas"
            },
            "cutscene": {
                "skeleton": "cutscene_char000296.skel",
                "atlas": "cutscene_char000296.atlas"
            },
            "dating": {
                "id": "7",
                "skeleton": "illust_dating7.skel",
                "atlas": "illust_dating7.atlas"
            }
        },
        {
            "id": "000301",
            "character": "Scheherazade",
            "costume": "The Lapis Witch",
            "character_image": "illust_inven_char000301_7.png",
            "skill_preview_image": "illust_skill_char000301_7.png",
            "standing": {
                "skeleton": "char000301.skel",
                "atlas": "char000301.atlas"
            },
            "cutscene": {
                "skeleton": "cutscene_char000301.skel",
                "atlas": "cutscene_char000301.atlas"
            },
            "dating": null
        },
        {
            "id": "000303",
            "character": "Scheherazade",
            "costume": "The Magic School Professor",
            "character_image": "illust_inven_char000303_43.png",
            "skill_preview_image": "illust_skill_char000303_43.png",
            "standing": {
                "skeleton": "char000303.skel",
                "atlas": "char000303.atlas"
            },
            "cutscene": {
                "skeleton": "cutscene_char000303.skel",
                "atlas": "cutscene_char000303.atlas"
            },
            "dating": null
        },
        {
            "id": "000304",
            "character": "Scheherazade",
            "costume": "Code Name S",
            "character_image": "illust_inven_char000304_48.png",
            "skill_preview_image": "illust_skill_char000304_48.png",
            "standing": {
                "skeleton": "char000304.skel",
                "atlas": "char000304.atlas"
            },
            "cutscene": {
                "skeleton": "cutscene_char000304.skel",
                "atlas": "cutscene_char000304.atlas"
            },
            "dating": null
        },
        {
            "id": "000306",
            "character": "Scheherazade",
            "costume": "Pool Party",
            "character_image": "illust_inven_char000306_92.png",
            "skill_preview_image": "illust_skill_char000306_92.png",
            "standing": {
                "skeleton": "char000306.skel",
                "atlas": "char000306.atlas"
            },
            "cutscene": {
                "skeleton": "cutscene_char000306.skel",
                "atlas": "cutscene_char000306.atlas"
            },
            "dating": null
        },
        {
            "id": "000401",
            "character": "Gray",
            "costume": "The Sharpshooter of the Mist",
            "character_image": "illust_inven_char000401_10.png",
            "skill_preview_image": "illust_skill_char000401_10.png",
            "standing": {
                "skeleton": "char000401.skel",
                "atlas": "char000401.atlas"
            },
            "cutscene": {
                "skeleton": "cutscene_char000401.skel",
                "atlas": "cutscene_char000401.atlas"
            },
            "dating": null
        },
        {
            "id": "000402",
            "character": "Gray",
            "costume": "B-Rank Manager",
            "character_image": "illust_inven_char000402_24.png",
            "skill_preview_image": "illust_skill_char000402_24.png",
            "standing": {
                "skeleton": "char000402.skel.skel",
                "atlas": "char000402.skel.atlas"
            },
            "cutscene": null,
            "dating": null
        },
        {
            "id": "000403",
            "character": "Gray",
            "costume": "Vanguard",
            "character_image": "illust_inven_char000403_70.png",
            "skill_preview_image": "illust_skill_char000403_70.png",
            "standing": {
                "skeleton": "char000403.skel",
                "atlas": "char000403.atlas"
            },
            "cutscene": null,
            "dating": null
        },
        {
            "id": "000406",
            "character": "Gray",
            "costume": "Pool Party",
            "character_image": "illust_inven_char000406_93.png",
            "skill_preview_image": "illust_skill_char000406_93.png",
            "standing": {
                "skeleton": "char000406.skel",
                "atlas": "char000406.atlas"
            },
            "cutscene": null,
            "dating": null
        },
        {
            "id": "000501",
            "character": "Rou",
            "costume": "White Cat",
            "character_image": "illust_inven_char000501_13.png",
            "skill_preview_image": "illust_skill_char000501_13.png",
            "standing": {
                "skeleton": "char000501.skel",
                "atlas": "char000501.atlas"
            },
            "cutscene": {
                "skeleton": "cutscene_char000501.skel",
                "atlas": "cutscene_char000501.atlas"
            },
            "dating": null
        },
        {
            "id": "000502",
            "character": "Rou",
            "costume": "Red Hat",
            "character_image": "illust_inven_char000502_98.png",
            "skill_preview_image": "illust_skill_char000502_98.png",
            "standing": {
                "skeleton": "char000502.skel",
                "atlas": "char000502.atlas"
            },
            "cutscene": {
                "skeleton": "cutscene_char000502.skel",
                "atlas": "cutscene_char000502.atlas"
            },
            "dating": null
        },
        {
            "id": "000504",
            "character": "Rou",
            "costume": "Nature's Claw",
            "character_image": "illust_inven_char000504_71.png",
            "skill_preview_image": "illust_skill_char000504_71.png",
            "standing": {
                "skeleton": "char000504.skel",
                "atlas": "char000504.atlas"
            },
            "cutscene": {
                "skeleton": "CutScene_Char000504.skel",
                "atlas": "CutScene_Char000504.atlas"
            },
            "dating": null
        },
        {
            "id": "000506",
            "character": "Rou",
            "costume": "Stray Cat",
            "character_image": "illust_inven_char000506_107.png",
            "skill_preview_image": "illust_skill_char000506_107.png",
            "standing": {
                "skeleton": "char000506.skel",
                "atlas": "char000506.atlas"
            },
            "cutscene": {
                "skeleton": "cutscene_char000506.skel",
                "atlas": "cutscene_char000506.atlas"
            },
            "dating": null
        },
        {
            "id": "000601",
            "character": "Olstein",
            "costume": "The Fiend Scholar",
            "character_image": "illust_inven_char000601_14.png",
            "skill_preview_image": "illust_skill_char000601_14.png",
            "standing": {
                "skeleton": "char000601.skel",
                "atlas": "char000601.atlas"
            },
            "cutscene": null,
            "dating": null
        },
        {
            "id": "000604",
            "character": "Olstein",
            "costume": "Sage of Blue Clouds",
            "character_image": "illust_inven_char000604_72.png",
            "skill_preview_image": "illust_skill_char000604_72.png",
            "standing": {
                "skeleton": "char000604.skel",
                "atlas": "char000604.atlas"
            },
            "cutscene": {
                "skeleton": "cutscene_char000604.skel",
                "atlas": "cutscene_char000604.atlas"
            },
            "dating": null
        },
        {
            "id": "000701",
            "character": "Eclipse",
            "costume": "Dimension Witch",
            "character_image": "illust_inven_char000701_20.png",
            "skill_preview_image": "illust_skill_char000701_20.png",
            "standing": {
                "skeleton": "char000701.skel",
                "atlas": "char000701.atlas"
            },
            "cutscene": {
                "skeleton": "cutscene_char000701.skel",
                "atlas": "cutscene_char000701.atlas"
            },
            "dating": null
        },
        {
            "id": "000706",
            "character": "Eclipse",
            "costume": "Nightmare Bunny",
            "character_image": "illust_inven_char000706_106.png",
            "skill_preview_image": "illust_skill_char000706_106.png",
            "standing": {
                "skeleton": "char000706.skel",
                "atlas": "char000706.atlas"
            },
            "cutscene": {
                "skeleton": "cutscene_char000706.skel",
                "atlas": "cutscene_char000706.atlas"
            },
            "dating": null
        },
        {
            "id": "000707",
            "character": "Eclipse",
            "costume": "Beach Vacation",
            "character_image": "illust_inven_char000707_134.png",
            "skill_preview_image": "illust_skill_char000707_134.png",
            "standing": {
                "skeleton": "char000707.skel",
                "atlas": "char000707.atlas"
            },
            "cutscene": {
                "skeleton": "cutscene_char000707.skel",
                "atlas": "cutscene_char000707.atlas"
            },
            "dating": null
        },
        {
            "id": "000708",
            "character": "Eclipse",
            "costume": "Dream Bride",
            "character_image": "illust_inven_char000708_170.png",
            "skill_preview_image": "illust_skill_char000708_170.png",
            "standing": {
                "skeleton": "char000708.skel",
                "atlas": "char000708.atlas"
            },
            "cutscene": {
                "skeleton": "cutscene_char000708.skel",
                "atlas": "cutscene_char000708.atlas"
            },
            "dating": null
        },
        {
            "id": "000801",
            "character": "Rubia",
            "costume": "Thorn of the Desert",
            "character_image": "illust_inven_char000801_21.png",
            "skill_preview_image": "illust_skill_char000801_21.png",
            "standing": {
                "skeleton": "char000801.skel",
                "atlas": "char000801.atlas"
            },
            "cutscene": {
                "skeleton": "cutscene_char000801.skel",
                "atlas": "cutscene_char000801.atlas"
            },
            "dating": null
        },
        {
            "id": "000804",
            "character": "Rubia",
            "costume": "The Empress of the Ocean",
            "character_image": "illust_inven_char000804_74.png",
            "skill_preview_image": "illust_skill_char000804_74.png",
            "standing": {
                "skeleton": "char000804.skel",
                "atlas": "char000804.atlas"
            },
            "cutscene": {
                "skeleton": "cutscene_char000804.skel",
                "atlas": "cutscene_char000804.atlas"
            },
            "dating": null
        },
        {
            "id": "000806",
            "character": "Rubia",
            "costume": "Maid Name C",
            "character_image": "illust_inven_char000806_116.png",
            "skill_preview_image": "illust_skill_char000806_116.png",
            "standing": {
                "skeleton": "char000806.skel",
                "atlas": "char000806.atlas"
            },
            "cutscene": {
                "skeleton": "cutscene_char000806.skel",
                "atlas": "cutscene_char000806.atlas"
            },
            "dating": null
        },
        {
            "id": "001001",
            "character": "Sylvia",
            "costume": "Desert Flower",
            "character_image": "illust_inven_char001001_22.png",
            "skill_preview_image": "illust_skill_char001001_22.png",
            "standing": {
                "skeleton": "char001001.skel",
                "atlas": "char001001.atlas"
            },
            "cutscene": {
                "skeleton": "cutscene_char001001.skel",
                "atlas": "cutscene_char001001.atlas"
            },
            "dating": null
        },
        {
            "id": "001002",
            "character": "Sylvia",
            "costume": "The Sword Queen",
            "character_image": "illust_inven_char001002_102.png",
            "skill_preview_image": "illust_skill_char001002_102.png",
            "standing": {
                "skeleton": "char001002.skel",
                "atlas": "char001002.atlas"
            },
            "cutscene": {
                "skeleton": "cutscene_char001002.skel",
                "atlas": "cutscene_char001002.atlas"
            },
            "dating": null
        },
        {
            "id": "001004",
            "character": "Sylvia",
            "costume": "Admiral",
            "character_image": "illust_inven_char001004_73.png",
            "skill_preview_image": "illust_skill_char001004_73.png",
            "standing": {
                "skeleton": "char001004.skel",
                "atlas": "char001004.atlas"
            },
            "cutscene": {
                "skeleton": "cutscene_char001004.skel",
                "atlas": "cutscene_char001004.atlas"
            },
            "dating": null
        },
        {
            "id": "001101",
            "character": "Teresse",
            "costume": "Angel of Destruction",
            "character_image": "illust_inven_char001101_57.png",
            "skill_preview_image": "illust_skill_char001101_57.png",
            "standing": {
                "skeleton": "char001101.skel",
                "atlas": "char001101.atlas"
            },
            "cutscene": {
                "skeleton": "cutscene_char001101.skel",
                "atlas": "cutscene_char001101.atlas"
            },
            "dating": null
        },
        {
            "id": "001106",
            "character": "Teresse",
            "costume": "Medical Club",
            "character_image": "illust_inven_char001106_117.png",
            "skill_preview_image": "illust_skill_char001106_117.png",
            "standing": {
                "skeleton": "char001106.skel",
                "atlas": "char001106.atlas"
            },
            "cutscene": {
                "skeleton": "cutscene_char001106.skel",
                "atlas": "cutscene_char001106.atlas"
            },
            "dating": {
                "id": "4",
                "skeleton": "illust_dating4.skel",
                "atlas": "illust_dating4.atlas"
            }
        },
        {
            "id": "001107",
            "character": "Teresse",
            "costume": "Beachside Angel",
            "character_image": "illust_inven_char001107_135.png",
            "skill_preview_image": "illust_skill_char001107_135.png",
            "standing": {
                "skeleton": "char001107.skel",
                "atlas": "char001107.atlas"
            },
            "cutscene": {
                "skeleton": "cutscene_char001107.skel",
                "atlas": "cutscene_char001107.atlas"
            },
            "dating": null
        },
        {
            "id": "001201",
            "character": "Liatris",
            "costume": "Rodev's Star",
            "character_image": "illust_inven_char001201_23.png",
            "skill_preview_image": "illust_skill_char001201_23.png",
            "standing": {
                "skeleton": "char001201.skel",
                "atlas": "char001201.atlas"
            },
            "cutscene": {
                "skeleton": "CutScene_Char001201.skel",
                "atlas": "CutScene_Char001201.atlas"
            },
            "dating": null
        },
        {
            "id": "001206",
            "character": "Liatris",
            "costume": "Neon Stalker",
            "character_image": "illust_inven_char001206_97.png",
            "skill_preview_image": "illust_skill_char001206_97.png",
            "standing": {
                "skeleton": "char001206.skel",
                "atlas": "char001206.atlas"
            },
            "cutscene": {
                "skeleton": "cutscene_char001206.skel",
                "atlas": "cutscene_char001206.atlas"
            },
            "dating": null
        },
        {
            "id": "001207",
            "character": "Liatris",
            "costume": "Maid Name R",
            "character_image": "illust_inven_char001207_114.png",
            "skill_preview_image": "illust_skill_char001207_114.png",
            "standing": {
                "skeleton": "char001207.skel",
                "atlas": "char001207.atlas"
            },
            "cutscene": {
                "skeleton": "cutscene_char001207.skel",
                "atlas": "cutscene_char001207.atlas"
            },
            "dating": null
        },
        {
            "id": "002401",
            "character": "Diana",
            "costume": "Adventurer of the Unknown",
            "character_image": "illust_inven_char002401_58.png",
            "skill_preview_image": "illust_skill_char002401_58.png",
            "standing": {
                "skeleton": "char002401.skel",
                "atlas": "char002401.atlas"
            },
            "cutscene": {
                "skeleton": "cutscene_char002401.skel",
                "atlas": "cutscene_char002401.atlas"
            },
            "dating": null
        },
        {
            "id": "002406",
            "character": "Diana",
            "costume": "Anti-dystopia",
            "character_image": "illust_inven_char002406_108.png",
            "skill_preview_image": "illust_skill_char002406_108.png",
            "standing": {
                "skeleton": "char002406.skel",
                "atlas": "char002406.atlas"
            },
            "cutscene": {
                "skeleton": "cutscene_char002406.skel",
                "atlas": "cutscene_char002406.atlas"
            },
            "dating": null
        },
        {
            "id": "003001",
            "character": "Layla",
            "costume": "Anvil of Creation",
            "character_image": "illust_inven_char003001_77.png",
            "skill_preview_image": "illust_skill_char003001_77.png",
            "standing": {
                "skeleton": "char003001.skel",
                "atlas": "char003001.atlas"
            },
            "cutscene": null,
            "dating": null
        },
        {
            "id": "003101",
            "character": "Elpis",
            "costume": "Hand of Salvation",
            "character_image": "illust_inven_char003101_122.png",
            "skill_preview_image": "illust_skill_char003101_122.png",
            "standing": {
                "skeleton": "char003101.skel",
                "atlas": "char003101.atlas"
            },
            "cutscene": {
                "skeleton": "cutscene_char003101.skel",
                "atlas": "cutscene_char003101.atlas"
            },
            "dating": null
        },
        {
            "id": "003201",
            "character": "Loen",
            "costume": "Last Hope",
            "character_image": "illust_inven_char003201_123.png",
            "skill_preview_image": "illust_skill_char003201_123.png",
            "standing": null,
            "cutscene": {
                "skeleton": "cutscene_char003201.skel",
                "atlas": "cutscene_char003201.atlas"
            },
            "dating": null
        },
        {
            "id": "003202",
            "character": "Loen",
            "costume": "Track and Field Team",
            "character_image": "illust_inven_char003202_133.png",
            "skill_preview_image": "illust_skill_char003202_133.png",
            "standing": {
                "skeleton": "char003202.skel",
                "atlas": "char003202.atlas"
            },
            "cutscene": {
                "skeleton": "cutscene_char003202.skel",
                "atlas": "cutscene_char003202.atlas"
            },
            "dating": null
        },
        {
            "id": "003203",
            "character": "Loen",
            "costume": "Celebrity Bunny",
            "character_image": "illust_inven_char003203_153.png",
            "skill_preview_image": "illust_skill_char003203_153.png",
            "standing": {
                "skeleton": "char003203.skel",
                "atlas": "char003203.atlas"
            },
            "cutscene": {
                "skeleton": "cutscene_char003203.skel",
                "atlas": "cutscene_char003203.atlas"
            },
            "dating": {
                "id": "3",
                "skeleton": "illust_dating3.skel",
                "atlas": "illust_dating3.atlas"
            }
        },
        {
            "id": "003301",
            "character": "Nebris",
            "costume": "Labyrinth Gatekeeper",
            "character_image": "illust_inven_char003301_146.png",
            "skill_preview_image": "illust_skill_char003301_146.png",
            "standing": {
                "skeleton": "char003301.skel",
                "atlas": "char003301.atlas"
            },
            "cutscene": {
                "skeleton": "cutscene_char003301.skel",
                "atlas": "cutscene_char003301.atlas"
            },
            "dating": null
        },
        {
            "id": "003302",
            "character": "Nebris",
            "costume": "Laid-back Lifeguard",
            "character_image": "illust_inven_char003302_130.png",
            "skill_preview_image": "illust_skill_char003302_130.png",
            "standing": {
                "skeleton": "char003302.skel",
                "atlas": "char003302.atlas"
            },
            "cutscene": {
                "skeleton": "cutscene_char003302.skel",
                "atlas": "cutscene_char003302.atlas"
            },
            "dating": null
        },
        {
            "id": "003303",
            "character": "Nebris",
            "costume": "New Hire",
            "character_image": "illust_inven_char003303_149.png",
            "skill_preview_image": "illust_skill_char003303_149.png",
            "standing": {
                "skeleton": "char003303.skel",
                "atlas": "char003303.atlas"
            },
            "cutscene": {
                "skeleton": "cutscene_char003303.skel",
                "atlas": "cutscene_char003303.atlas"
            },
            "dating": {
                "id": "1",
                "skeleton": "illust_dating1.skel",
                "atlas": "illust_dating1.atlas"
            }
        },
        {
            "id": "003401",
            "character": "Morpeah",
            "costume": "Beach Vacation",
            "character_image": "illust_inven_char003401_136.png",
            "skill_preview_image": "illust_skill_char003401_136.png",
            "standing": {
                "skeleton": "char003401.skel",
                "atlas": "char003401.atlas"
            },
            "cutscene": {
                "skeleton": "cutscene_char003401.skel",
                "atlas": "cutscene_char003401.atlas"
            },
            "dating": null
        },
        {
            "id": "003402",
            "character": "Morpeah",
            "costume": "Daydream Bunny",
            "character_image": "illust_inven_char003402_152.png",
            "skill_preview_image": "illust_skill_char003402_152.png",
            "standing": {
                "skeleton": "char003402.skel",
                "atlas": "char003402.atlas"
            },
            "cutscene": {
                "skeleton": "cutscene_char003402.skel",
                "atlas": "cutscene_char003402.atlas"
            },
            "dating": {
                "id": "2",
                "skeleton": "illust_dating2.skel",
                "atlas": "illust_dating2.atlas"
            }
        },
        {
            "id": "003403",
            "character": "Morpeah",
            "costume": "Apostle",
            "character_image": "illust_inven_char003403_169.png",
            "skill_preview_image": "illust_skill_char003403_169.png",
            "standing": {
                "skeleton": "char003403.skel",
                "atlas": "char003403.atlas"
            },
            "cutscene": {
                "skeleton": "cutscene_char003403.skel",
                "atlas": "cutscene_char003403.atlas"
            },
            "dating": null
        },
        {
            "id": "003501",
            "character": "Sacred Justia",
            "costume": "Reclaimed Destiny",
            "character_image": "illust_inven_char003501_131.png",
            "skill_preview_image": "illust_skill_char003501_131.png",
            "standing": {
                "skeleton": "char003501.skel",
                "atlas": "char003501.atlas"
            },
            "cutscene": {
                "skeleton": "cutscene_char003501.skel",
                "atlas": "cutscene_char003501.atlas"
            },
            "dating": null
        },
        {
            "id": "003701",
            "character": "Blade",
            "costume": "Apostle",
            "character_image": "illust_inven_char003701_165.png",
            "skill_preview_image": "illust_skill_char003701_165.png",
            "standing": {
                "skeleton": "char003701.skel",
                "atlas": "char003701.atlas"
            },
            "cutscene": {
                "skeleton": "cutscene_char003701.skel",
                "atlas": "cutscene_char003701.atlas"
            },
            "dating": null
        },
        {
            "id": "003703",
            "character": "Blade",
            "costume": "Young Lady",
            "character_image": "illust_inven_char003703_166.png",
            "skill_preview_image": "illust_skill_char003703_166.png",
            "standing": {
                "skeleton": "char003703.skel",
                "atlas": "char003703.atlas"
            },
            "cutscene": {
                "skeleton": "cutscene_char003703.skel",
                "atlas": "cutscene_char003703.atlas"
            },
            "dating": null
        },
        {
            "id": "003801",
            "character": "Liberta",
            "costume": "Dark Saintess",
            "character_image": "illust_inven_char003801_164.png",
            "skill_preview_image": "illust_skill_char003801_164.png",
            "standing": {
                "skeleton": "char003801.skel",
                "atlas": "char003801.atlas"
            },
            "cutscene": {
                "skeleton": "cutscene_char003801.skel",
                "atlas": "cutscene_char003801.atlas"
            },
            "dating": null
        },
        {
            "id": "003802",
            "character": "Liberta",
            "costume": "Onsen Manager",
            "character_image": "illust_inven_char003802_159.png",
            "skill_preview_image": "illust_skill_char003802_159.png",
            "standing": {
                "skeleton": "char003802.skel",
                "atlas": "char003802.atlas"
            },
            "cutscene": {
                "skeleton": "cutscene_char003802.skel",
                "atlas": "cutscene_char003802.atlas"
            },
            "dating": null
        },
        {
            "id": "020001",
            "character": "Eris",
            "costume": "Esteemed Adventurer",
            "character_image": "illust_inven_char020001_124.png",
            "skill_preview_image": "illust_skill_char020001_124.png",
            "standing": {
                "skeleton": "char020001.skel",
                "atlas": "char020001.atlas"
            },
            "cutscene": {
                "skeleton": "cutscene_char020001.skel",
                "atlas": "cutscene_char020001.atlas"
            },
            "dating": null
        },
        {
            "id": "020002",
            "character": "Eris",
            "costume": "Your Very Own Cat",
            "character_image": "illust_inven_char020002_127.png",
            "skill_preview_image": "illust_skill_char020002_127.png",
            "standing": {
                "skeleton": "char020002.skel",
                "atlas": "char020002.atlas"
            },
            "cutscene": {
                "skeleton": "cutscene_char020002.skel",
                "atlas": "cutscene_char020002.atlas"
            },
            "dating": null
        },
        {
            "id": "020101",
            "character": "Roxy",
            "costume": "Respected Master",
            "character_image": "illust_inven_char020101_125.png",
            "skill_preview_image": "illust_skill_char020101_125.png",
            "standing": {
                "skeleton": "char020101.skel",
                "atlas": "char020101.atlas"
            },
            "cutscene": {
                "skeleton": "cutscene_char020101.skel",
                "atlas": "cutscene_char020101.atlas"
            },
            "dating": null
        },
        {
            "id": "020102",
            "character": "Roxy",
            "costume": "Emerging Desire",
            "character_image": "illust_inven_char020102_126.png",
            "skill_preview_image": "illust_skill_char020102_126.png",
            "standing": {
                "skeleton": "char020102.skel",
                "atlas": "char020102.atlas"
            },
            "cutscene": {
                "skeleton": "cutscene_char020102.skel",
                "atlas": "cutscene_char020102.atlas"
            },
            "dating": null
        },
        {
            "id": "020201",
            "character": "Yomi",
            "costume": "Gentle Destroyer",
            "character_image": "illust_inven_char020201_140.png",
            "skill_preview_image": "illust_skill_char020201_140.png",
            "standing": {
                "skeleton": "char020201.skel",
                "atlas": "char020201.atlas"
            },
            "cutscene": {
                "skeleton": "cutscene_char020201.skel",
                "atlas": "cutscene_char020201.atlas"
            },
            "dating": null
        },
        {
            "id": "020301",
            "character": "Yozakura",
            "costume": "Fist of Conviction",
            "character_image": "illust_inven_char020301_141.png",
            "skill_preview_image": "illust_skill_char020301_141.png",
            "standing": {
                "skeleton": "char020301.skel",
                "atlas": "char020301.atlas"
            },
            "cutscene": {
                "skeleton": "cutscene_char020301.skel",
                "atlas": "cutscene_char020301.atlas"
            },
            "dating": null
        },
        {
            "id": "020401",
            "character": "Yumi",
            "costume": "Dancing Snowflake",
            "character_image": "illust_inven_char020401_142.png",
            "skill_preview_image": "illust_skill_char020401_142.png",
            "standing": {
                "skeleton": "char020401.skel",
                "atlas": "char020401.atlas"
            },
            "cutscene": {
                "skeleton": "cutscene_char020401.skel",
                "atlas": "cutscene_char020401.atlas"
            },
            "dating": null
        },
        {
            "id": "020501",
            "character": "Hikage",
            "costume": "Kind Ruthlessness",
            "character_image": "illust_inven_char020501_143.png",
            "skill_preview_image": "illust_skill_char020501_143.png",
            "standing": {
                "skeleton": "char020501.skel",
                "atlas": "char020501.atlas"
            },
            "cutscene": {
                "skeleton": "cutscene_char020501.skel",
                "atlas": "cutscene_char020501.atlas"
            },
            "dating": null
        },
        {
            "id": "020601",
            "character": "Goblin Slayer",
            "costume": "Orcbolg",
            "character_image": "illust_inven_char020601_160.png",
            "skill_preview_image": "illust_skill_char020601_160.png",
            "standing": {
                "skeleton": "char020601.skel",
                "atlas": "char020601.atlas"
            },
            "cutscene": {
                "skeleton": "cutscene_char020601.skel",
                "atlas": "cutscene_char020601.atlas"
            },
            "dating": null
        },
        {
            "id": "020701",
            "character": "Priestess",
            "costume": "Earth Mother Believer",
            "character_image": "illust_inven_char020701_161.png",
            "skill_preview_image": "illust_skill_char020701_161.png",
            "standing": {
                "skeleton": "char020701.skel",
                "atlas": "char020701.atlas"
            },
            "cutscene": {
                "skeleton": "cutscene_char020701.skel",
                "atlas": "cutscene_char020701.atlas"
            },
            "dating": null
        },
        {
            "id": "020801",
            "character": "High Elf Archer",
            "costume": "Daughter of Starwind",
            "character_image": "illust_inven_char020801_162.png",
            "skill_preview_image": "illust_skill_char020801_162.png",
            "standing": {
                "skeleton": "char020801.skel",
                "atlas": "char020801.atlas"
            },
            "cutscene": {
                "skeleton": "cutscene_char020801.skel",
                "atlas": "cutscene_char020801.atlas"
            },
            "dating": null
        },
        {
            "id": "020901",
            "character": "Sword Maiden",
            "costume": "Supreme God Archbishop",
            "character_image": "illust_inven_char020901_163.png",
            "skill_preview_image": "illust_skill_char020901_163.png",
            "standing": {
                "skeleton": "char020901.skel",
                "atlas": "char020901.atlas"
            },
            "cutscene": {
                "skeleton": "cutscene_char020901.skel",
                "atlas": "cutscene_char020901.atlas"
            },
            "dating": null
        },
        {
            "id": "060301",
            "character": "Alec",
            "costume": "The Destruction",
            "character_image": "illust_inven_char060301_60.png",
            "skill_preview_image": "illust_skill_char060301_60.png",
            "standing": {
                "skeleton": "char060301.skel",
                "atlas": "char060301.atlas"
            },
            "cutscene": null,
            "dating": null
        },
        {
            "id": "060302",
            "character": "Alec",
            "costume": "Sword Breaker",
            "character_image": "illust_inven_char060302_56.png",
            "skill_preview_image": "illust_skill_char060302_56.png",
            "standing": {
                "skeleton": "char060302.skel",
                "atlas": "char060302.atlas"
            },
            "cutscene": null,
            "dating": null
        },
        {
            "id": "060402",
            "character": "Celia",
            "costume": "Descendant of the Great Witch",
            "character_image": "illust_inven_char060402_28.png",
            "skill_preview_image": "illust_skill_char060402_28.png",
            "standing": {
                "skeleton": "char060402.skel",
                "atlas": "char060402.atlas"
            },
            "cutscene": {
                "skeleton": "cutscene_char060402.skel",
                "atlas": "cutscene_char060402.atlas"
            },
            "dating": null
        },
        {
            "id": "060403",
            "character": "Celia",
            "costume": "Masquerade Bunny",
            "character_image": "illust_inven_char060403_109.png",
            "skill_preview_image": "illust_skill_char060403_109.png",
            "standing": {
                "skeleton": "char060403.skel",
                "atlas": "char060403.atlas"
            },
            "cutscene": {
                "skeleton": "cutscene_char060403.skel",
                "atlas": "cutscene_char060403.atlas"
            },
            "dating": null
        },
        {
            "id": "060501",
            "character": "Anatasia",
            "costume": "Gentle Maid",
            "character_image": "illust_inven_char060501_79.png",
            "skill_preview_image": "illust_skill_char060501_79.png",
            "standing": {
                "skeleton": "char060501.skel",
                "atlas": "char060501.atlas"
            },
            "cutscene": {
                "skeleton": "cutscene_char060501.skel",
                "atlas": "cutscene_char060501.atlas"
            },
            "dating": null
        },
        {
            "id": "060502",
            "character": "Anatasia",
            "costume": "Fire Graffiti",
            "character_image": "illust_inven_char060502_46.png",
            "skill_preview_image": "illust_skill_char060502_46.png",
            "standing": {
                "skeleton": "char060502.skel",
                "atlas": "char060502.atlas"
            },
            "cutscene": {
                "skeleton": "cutscene_char060502.skel",
                "atlas": "cutscene_char060502.atlas"
            },
            "dating": null
        },
        {
            "id": "060601",
            "character": "Lecliss",
            "costume": "Killer Doll",
            "character_image": "illust_inven_char060601_80.png",
            "skill_preview_image": "illust_skill_char060601_80.png",
            "standing": {
                "skeleton": "char060601.skel",
                "atlas": "char060601.atlas"
            },
            "cutscene": {
                "skeleton": "cutscene_char060601.skel",
                "atlas": "cutscene_char060601.atlas"
            },
            "dating": null
        },
        {
            "id": "060602",
            "character": "Lecliss",
            "costume": "Android Queen",
            "character_image": "illust_inven_char060602_47.png",
            "skill_preview_image": "illust_skill_char060602_47.png",
            "standing": {
                "skeleton": "char060602.skel",
                "atlas": "char060602.atlas"
            },
            "cutscene": {
                "skeleton": "cutscene_char060602.skel",
                "atlas": "cutscene_char060602.atlas"
            },
            "dating": null
        },
        {
            "id": "060701",
            "character": "Rafina",
            "costume": "Steel Engine",
            "character_image": "illust_inven_char060701_81.png",
            "skill_preview_image": "illust_skill_char060701_81.png",
            "standing": {
                "skeleton": "char060701.skel",
                "atlas": "char060701.atlas"
            },
            "cutscene": null,
            "dating": null
        },
        {
            "id": "060702",
            "character": "Rafina",
            "costume": "Code Name A",
            "character_image": "illust_inven_char060702_49.png",
            "skill_preview_image": "illust_skill_char060702_49.png",
            "standing": {
                "skeleton": "char060702.skel",
                "atlas": "char060702.atlas"
            },
            "cutscene": null,
            "dating": null
        },
        {
            "id": "060706",
            "character": "Rafina",
            "costume": "Game Club",
            "character_image": "illust_inven_char060706_118.png",
            "skill_preview_image": "illust_skill_char060706_118.png",
            "standing": {
                "skeleton": "char060706.skel",
                "atlas": "char060706.atlas"
            },
            "cutscene": {
                "skeleton": "cutscene_char060706.skel",
                "atlas": "cutscene_char060706.atlas"
            },
            "dating": null
        },
        {
            "id": "060801",
            "character": "Elise",
            "costume": "Lovely Lady",
            "character_image": "illust_inven_char060801_82.png",
            "skill_preview_image": "illust_skill_char060801_82.png",
            "standing": {
                "skeleton": "char060801.skel",
                "atlas": "char060801.atlas"
            },
            "cutscene": {
                "skeleton": "cutscene_char060801.skel",
                "atlas": "cutscene_char060801.atlas"
            },
            "dating": null
        },
        {
            "id": "060802",
            "character": "Elise",
            "costume": "Code Name O",
            "character_image": "illust_inven_char060802_50.png",
            "skill_preview_image": "illust_skill_char060802_50.png",
            "standing": {
                "skeleton": "char060802.skel",
                "atlas": "char060802.atlas"
            },
            "cutscene": {
                "skeleton": "cutscene_char060802.skel",
                "atlas": "cutscene_char060802.atlas"
            },
            "dating": {
                "id": "5",
                "skeleton": "illust_dating5.skel",
                "atlas": "illust_dating5.atlas"
            }
        },
        {
            "id": "061001",
            "character": "Helena",
            "costume": "Top Idol",
            "character_image": "illust_inven_char061001_83.png",
            "skill_preview_image": "illust_skill_char061001_83.png",
            "standing": {
                "skeleton": "char061001.skel",
                "atlas": "char061001.atlas"
            },
            "cutscene": {
                "skeleton": "cutscene_char061001.skel",
                "atlas": "cutscene_char061001.atlas"
            },
            "dating": null
        },
        {
            "id": "061002",
            "character": "Helena",
            "costume": "B-Rank Idol",
            "character_image": "illust_inven_char061002_26.png",
            "skill_preview_image": "illust_skill_char061002_26.png",
            "standing": {
                "skeleton": "char061002.skel",
                "atlas": "char061002.atlas"
            },
            "cutscene": {
                "skeleton": "cutscene_Char061002.skel",
                "atlas": "cutscene_Char061002.atlas"
            },
            "dating": null
        },
        {
            "id": "061101",
            "character": "Eleaneer",
            "costume": "Piercing Magic Bow",
            "character_image": "illust_inven_char061101_84.png",
            "skill_preview_image": "illust_skill_char061101_84.png",
            "standing": {
                "skeleton": "char061101.skel",
                "atlas": "char061101.atlas"
            },
            "cutscene": {
                "skeleton": "cutscene_char061101.skel",
                "atlas": "cutscene_char061101.atlas"
            },
            "dating": null
        },
        {
            "id": "061102",
            "character": "Eleaneer",
            "costume": "B-Rank Idol",
            "character_image": "illust_inven_char061102_27.png",
            "skill_preview_image": "illust_skill_char061102_27.png",
            "standing": {
                "skeleton": "char061102.skel",
                "atlas": "char061102.atlas"
            },
            "cutscene": {
                "skeleton": "cutscene_char061102.skel",
                "atlas": "cutscene_char061102.atlas"
            },
            "dating": null
        },
        {
            "id": "061302",
            "character": "Dalvi",
            "costume": "Bright Moon",
            "character_image": "illust_inven_char061302_104.png",
            "skill_preview_image": "illust_skill_char061302_104.png",
            "standing": {
                "skeleton": "char061302.skel",
                "atlas": "char061302.atlas"
            },
            "cutscene": {
                "skeleton": "cutscene_char061302.skel",
                "atlas": "cutscene_char061302.atlas"
            },
            "dating": null
        },
        {
            "id": "061305",
            "character": "Dalvi",
            "costume": "Summer Vacation",
            "character_image": "illust_inven_char061305_128.png",
            "skill_preview_image": "illust_skill_char061305_128.png",
            "standing": {
                "skeleton": "char061305.skel",
                "atlas": "char061305.atlas"
            },
            "cutscene": {
                "skeleton": "cutscene_char061305.skel",
                "atlas": "cutscene_char061305.atlas"
            },
            "dating": null
        },
        {
            "id": "061402",
            "character": "Zenith",
            "costume": "Robin Hood",
            "character_image": "illust_inven_char061402_101.png",
            "skill_preview_image": "illust_skill_char061402_101.png",
            "standing": {
                "skeleton": "char061402.skel",
                "atlas": "char061402.atlas"
            },
            "cutscene": {
                "skeleton": "cutscene_char061402.skel",
                "atlas": "cutscene_char061402.atlas"
            },
            "dating": null
        },
        {
            "id": "061404",
            "character": "Zenith",
            "costume": "Poolside Guardian",
            "character_image": "illust_inven_char061404_172.png",
            "skill_preview_image": "illust_skill_char061404_172.png",
            "standing": {
                "skeleton": "char061404.skel",
                "atlas": "char061404.atlas"
            },
            "cutscene": null,
            "dating": null
        },
        {
            "id": "062001",
            "character": "Andrew",
            "costume": "Loyal Butler",
            "character_image": "illust_inven_char062001_68.png",
            "skill_preview_image": "illust_skill_char062001_68.png",
            "standing": {
                "skeleton": "char062001.skel",
                "atlas": "char062001.atlas"
            },
            "cutscene": null,
            "dating": null
        },
        {
            "id": "062002",
            "character": "Andrew",
            "costume": "Specialist",
            "character_image": "illust_inven_char062002_51.png",
            "skill_preview_image": "illust_skill_char062002_51.png",
            "standing": {
                "skeleton": "char062002.skel",
                "atlas": "char062002.atlas"
            },
            "cutscene": null,
            "dating": null
        },
        {
            "id": "063001",
            "character": "Ingrid",
            "costume": "Kardis' Bullet",
            "character_image": "illust_inven_char063001_62.png",
            "skill_preview_image": "illust_skill_char063001_62.png",
            "standing": {
                "skeleton": "char063001.skel",
                "atlas": "char063001.atlas"
            },
            "cutscene": null,
            "dating": null
        },
        {
            "id": "063301",
            "character": "Cynthia",
            "costume": "Warmth within the Severe Cold",
            "character_image": "illust_inven_char063301_63.png",
            "skill_preview_image": "illust_skill_char063301_63.png",
            "standing": {
                "skeleton": "char063301.skel",
                "atlas": "char063301.atlas"
            },
            "cutscene": null,
            "dating": null
        },
        {
            "id": "063401",
            "character": "Julie",
            "costume": "Healer",
            "character_image": "illust_inven_char063401_64.png",
            "skill_preview_image": "illust_skill_char063401_64.png",
            "standing": {
                "skeleton": "char063401.skel",
                "atlas": "char063401.atlas"
            },
            "cutscene": null,
            "dating": null
        },
        {
            "id": "065102",
            "character": "Yuri",
            "costume": "Whitebolt",
            "character_image": "illust_inven_char065102_105.png",
            "skill_preview_image": "illust_skill_char065102_105.png",
            "standing": {
                "skeleton": "char065102.skel",
                "atlas": "char065102.atlas"
            },
            "cutscene": {
                "skeleton": "cutscene_char065102.skel",
                "atlas": "cutscene_char065102.atlas"
            },
            "dating": null
        },
        {
            "id": "065103",
            "character": "Yuri",
            "costume": "Comeback Idol",
            "character_image": "illust_inven_char065103_110.png",
            "skill_preview_image": "illust_skill_char065103_110.png",
            "standing": {
                "skeleton": "Char065103.skel",
                "atlas": "Char065103.atlas"
            },
            "cutscene": {
                "skeleton": "cutscene_char065103.skel",
                "atlas": "cutscene_char065103.atlas"
            },
            "dating": null
        },
        {
            "id": "065802",
            "character": "Nartas",
            "costume": "Anonymous Sage",
            "character_image": "illust_inven_char065802_103.png",
            "skill_preview_image": "illust_skill_char065802_103.png",
            "standing": {
                "skeleton": "char065802.skel",
                "atlas": "char065802.atlas"
            },
            "cutscene": {
                "skeleton": "cutscene_char065802.skel",
                "atlas": "cutscene_char065802.atlas"
            },
            "dating": null
        },
        {
            "id": "066401",
            "character": "Angelica",
            "costume": "The Fallen",
            "character_image": "illust_inven_char066401_94.png",
            "skill_preview_image": "illust_skill_char066401_94.png",
            "standing": {
                "skeleton": "char066401.skel",
                "atlas": "char066401.atlas"
            },
            "cutscene": {
                "skeleton": "cutscene_char066401.skel",
                "atlas": "cutscene_char066401.atlas"
            },
            "dating": null
        },
        {
            "id": "066402",
            "character": "Angelica",
            "costume": "Pool Party",
            "character_image": "illust_inven_char066402_95.png",
            "skill_preview_image": "illust_skill_char066402_95.png",
            "standing": {
                "skeleton": "char066402.skel",
                "atlas": "char066402.atlas"
            },
            "cutscene": {
                "skeleton": "cutscene_char066402.skel",
                "atlas": "cutscene_char066402.atlas"
            },
            "dating": null
        },
        {
            "id": "066403",
            "character": "Angelica",
            "costume": "Neon Savior",
            "character_image": "illust_inven_char066403_96.png",
            "skill_preview_image": "illust_skill_char066403_96.png",
            "standing": {
                "skeleton": "char066403.skel",
                "atlas": "char066403.atlas"
            },
            "cutscene": {
                "skeleton": "cutscene_char066403.skel",
                "atlas": "cutscene_char066403.atlas"
            },
            "dating": null
        },
        {
            "id": "066801",
            "character": "Refithea",
            "costume": "The Gluttonous",
            "character_image": "illust_inven_char066801_120.png",
            "skill_preview_image": "illust_skill_char066801_120.png",
            "standing": {
                "skeleton": "char066801.skel",
                "atlas": "char066801.atlas"
            },
            "cutscene": {
                "skeleton": "cutscene_char066801.skel",
                "atlas": "cutscene_char066801.atlas"
            },
            "dating": null
        },
        {
            "id": "066802",
            "character": "Refithea",
            "costume": "Pure White Blessing",
            "character_image": "illust_inven_char066802_121.png",
            "skill_preview_image": "illust_skill_char066802_121.png",
            "standing": {
                "skeleton": "char066802.skel",
                "atlas": "char066802.atlas"
            },
            "cutscene": {
                "skeleton": "cutscene_char066802.skel",
                "atlas": "cutscene_char066802.atlas"
            },
            "dating": null
        },
        {
            "id": "066803",
            "character": "Refithea",
            "costume": "Poolside Fairy",
            "character_image": "illust_inven_char066803_173.png",
            "skill_preview_image": "illust_skill_char066803_173.png",
            "standing": {
                "skeleton": "char066803.skel",
                "atlas": "char066803.atlas"
            },
            "cutscene": {
                "skeleton": "cutscene_char066803.skel",
                "atlas": "cutscene_char066803.atlas"
            },
            "dating": null
        },
        {
            "id": "066902",
            "character": "Glacia",
            "costume": "Alice",
            "character_image": "illust_inven_char066902_100.png",
            "skill_preview_image": "illust_skill_char066902_100.png",
            "standing": {
                "skeleton": "char066902.skel",
                "atlas": "char066902.atlas"
            },
            "cutscene": {
                "skeleton": "cutscene_char066902.skel",
                "atlas": "cutscene_char066902.atlas"
            },
            "dating": null
        },
        {
            "id": "066906",
            "character": "Glacia",
            "costume": "Disciplinary Committee",
            "character_image": "illust_inven_char066906_119.png",
            "skill_preview_image": "illust_skill_char066906_119.png",
            "standing": {
                "skeleton": "char066906.skel",
                "atlas": "char066906.atlas"
            },
            "cutscene": {
                "skeleton": "cutscene_char066906.skel",
                "atlas": "cutscene_char066906.atlas"
            },
            "dating": null
        },
        {
            "id": "067002",
            "character": "Ventana",
            "costume": "Snow White",
            "character_image": "illust_inven_char067002_99.png",
            "skill_preview_image": "illust_skill_char067002_99.png",
            "standing": {
                "skeleton": "char067002.skel",
                "atlas": "char067002.atlas"
            },
            "cutscene": {
                "skeleton": "cutscene_char067002.skel",
                "atlas": "cutscene_char067002.atlas"
            },
            "dating": null
        },
        {
            "id": "067003",
            "character": "Ventana",
            "costume": "Comeback Idol",
            "character_image": "illust_inven_char067003_111.png",
            "skill_preview_image": "illust_skill_char067003_111.png",
            "standing": {
                "skeleton": "Char067003.skel",
                "atlas": "Char067003.atlas"
            },
            "cutscene": {
                "skeleton": "cutscene_char067003.skel",
                "atlas": "cutscene_char067003.atlas"
            },
            "dating": null
        },
        {
            "id": "067004",
            "character": "Ventana",
            "costume": "Onsen Practitioner",
            "character_image": "illust_inven_char067004_157.png",
            "skill_preview_image": "illust_skill_char067004_157.png",
            "standing": {
                "skeleton": "char067004.skel",
                "atlas": "char067004.atlas"
            },
            "cutscene": {
                "skeleton": "cutscene_char067004.skel",
                "atlas": "cutscene_char067004.atlas"
            },
            "dating": null
        },
        {
            "id": "067101",
            "character": "Granhildr",
            "costume": "The Void",
            "character_image": "illust_inven_char067101_113.png",
            "skill_preview_image": "illust_skill_char067101_113.png",
            "standing": {
                "skeleton": "char067101.skel",
                "atlas": "char067101.atlas"
            },
            "cutscene": {
                "skeleton": "cutscene_char067101.skel",
                "atlas": "cutscene_char067101.atlas"
            },
            "dating": null
        },
        {
            "id": "067102",
            "character": "Granhildr",
            "costume": "Comeback Idol",
            "character_image": "illust_inven_char067102_112.png",
            "skill_preview_image": "illust_skill_char067102_112.png",
            "standing": {
                "skeleton": "char067102.skel",
                "atlas": "char067102.atlas"
            },
            "cutscene": {
                "skeleton": "cutscene_char067102.skel",
                "atlas": "cutscene_char067102.atlas"
            },
            "dating": null
        },
        {
            "id": "067201",
            "character": "Venaka",
            "costume": "DJ",
            "character_image": "illust_inven_char067201_129.png",
            "skill_preview_image": "illust_skill_char067201_129.png",
            "standing": {
                "skeleton": "char067201.skel",
                "atlas": "char067201.atlas"
            },
            "cutscene": {
                "skeleton": "cutscene_char067201.skel",
                "atlas": "cutscene_char067201.atlas"
            },
            "dating": null
        },
        {
            "id": "067202",
            "character": "Venaka",
            "costume": "Wind Dancer",
            "character_image": "illust_inven_char067202_147.png",
            "skill_preview_image": "illust_skill_char067202_147.png",
            "standing": {
                "skeleton": "char067202.skel",
                "atlas": "char067202.atlas"
            },
            "cutscene": {
                "skeleton": "cutscene_char067202.skel",
                "atlas": "cutscene_char067202.atlas"
            },
            "dating": null
        },
        {
            "id": "067301",
            "character": "Levia",
            "costume": "Track and Field Captain",
            "character_image": "illust_inven_char067301_132.png",
            "skill_preview_image": "illust_skill_char067301_132.png",
            "standing": {
                "skeleton": "char067301.skel",
                "atlas": "char067301.atlas"
            },
            "cutscene": {
                "skeleton": "cutscene_char067301.skel",
                "atlas": "cutscene_char067301.atlas"
            },
            "dating": null
        },
        {
            "id": "067302",
            "character": "Levia",
            "costume": "Night of Jealousy",
            "character_image": "illust_inven_char067302_139.png",
            "skill_preview_image": "illust_skill_char067302_139.png",
            "standing": {
                "skeleton": "char067302.skel",
                "atlas": "char067302.atlas"
            },
            "cutscene": {
                "skeleton": "cutscene_char067302.skel",
                "atlas": "cutscene_char067302.atlas"
            },
            "dating": null
        },
        {
            "id": "067303",
            "character": "Levia",
            "costume": "Overheat",
            "character_image": "illust_inven_char067303_154.png",
            "skill_preview_image": "illust_skill_char067303_154.png",
            "standing": {
                "skeleton": "char067303.skel",
                "atlas": "char067303.atlas"
            },
            "cutscene": {
                "skeleton": "cutscene_char067303.skel",
                "atlas": "cutscene_char067303.atlas"
            },
            "dating": null
        },
        {
            "id": "067401",
            "character": "Michaela",
            "costume": "Beachside Justice",
            "character_image": "illust_inven_char067401_137.png",
            "skill_preview_image": "illust_skill_char067401_137.png",
            "standing": {
                "skeleton": "char067401.skel",
                "atlas": "char067401.atlas"
            },
            "cutscene": {
                "skeleton": "cutscene_char067401.skel",
                "atlas": "cutscene_char067401.atlas"
            },
            "dating": null
        },
        {
            "id": "067402",
            "character": "Michaela",
            "costume": "Queen of Signatures",
            "character_image": "illust_inven_char067402_151.png",
            "skill_preview_image": "illust_skill_char067402_151.png",
            "standing": {
                "skeleton": "char067402.skel",
                "atlas": "char067402.atlas"
            },
            "cutscene": {
                "skeleton": "cutscene_char067402.skel",
                "atlas": "cutscene_char067402.atlas"
            },
            "dating": null
        },
        {
            "id": "067403",
            "character": "Michaela",
            "costume": "Acting Archbishop",
            "character_image": "illust_inven_char067403_168.png",
            "skill_preview_image": "illust_skill_char067403_168.png",
            "standing": {
                "skeleton": "char067403.skel",
                "atlas": "char067403.atlas"
            },
            "cutscene": {
                "skeleton": "cutscene_char067403.skel",
                "atlas": "cutscene_char067403.atlas"
            },
            "dating": null
        },
        {
            "id": "067502",
            "character": "Luvencia",
            "costume": "Deal Snatcher",
            "character_image": "illust_inven_char067502_148.png",
            "skill_preview_image": "illust_skill_char067502_148.png",
            "standing": {
                "skeleton": "char067502.skel",
                "atlas": "char067502.atlas"
            },
            "cutscene": {
                "skeleton": "cutscene_char067502.skel",
                "atlas": "cutscene_char067502.atlas"
            },
            "dating": null
        },
        {
            "id": "067503",
            "character": "Luvencia",
            "costume": "Wild Dog",
            "character_image": "illust_inven_char067503_155.png",
            "skill_preview_image": "illust_skill_char067503_155.png",
            "standing": {
                "skeleton": "char067503.skel",
                "atlas": "char067503.atlas"
            },
            "cutscene": {
                "skeleton": "cutscene_char067503.skel",
                "atlas": "cutscene_char067503.atlas"
            },
            "dating": null
        },
        {
            "id": "067601",
            "character": "Wilhelmina",
            "costume": "Iron Monarch",
            "character_image": "illust_inven_char067601_167.png",
            "skill_preview_image": "illust_skill_char067601_167.png",
            "standing": {
                "skeleton": "char067601.skel",
                "atlas": "char067601.atlas"
            },
            "cutscene": {
                "skeleton": "cutscene_char067601.skel",
                "atlas": "cutscene_char067601.atlas"
            },
            "dating": null
        },
        {
            "id": "067603",
            "character": "Wilhelmina",
            "costume": "Water Park Queen",
            "character_image": "illust_inven_char067603_171.png",
            "skill_preview_image": "illust_skill_char067603_171.png",
            "standing": {
                "skeleton": "char067603.skel",
                "atlas": "char067603.atlas"
            },
            "cutscene": {
                "skeleton": "cutscene_char067603.skel",
                "atlas": "cutscene_char067603.atlas"
            },
            "dating": {
                "id": "6",
                "skeleton": "illust_dating6.skel",
                "atlas": "illust_dating6.atlas"
            }
        },
        {
            "id": "100101",
            "character": "Gynt",
            "costume": "Lugo Hunter",
            "character_image": "illust_inven_char100101_4.png",
            "skill_preview_image": "illust_skill_char100101_4.png",
            "standing": {
                "skeleton": "char100101.skel",
                "atlas": "char100101.atlas"
            },
            "cutscene": null,
            "dating": null
        },
        {
            "id": "100201",
            "character": "Fred",
            "costume": "Lugo Defense Force",
            "character_image": "illust_inven_char100201_5.png",
            "skill_preview_image": "illust_skill_char100201_5.png",
            "standing": {
                "skeleton": "char100201.skel",
                "atlas": "char100201.atlas"
            },
            "cutscene": null,
            "dating": null
        },
        {
            "id": "100301",
            "character": "Lisianne",
            "costume": "Wandering Priest",
            "character_image": "illust_inven_char100301_6.png",
            "skill_preview_image": "illust_skill_char100301_6.png",
            "standing": {
                "skeleton": "char100301.skel",
                "atlas": "char100301.atlas"
            },
            "cutscene": null,
            "dating": null
        },
        {
            "id": "100401",
            "character": "Remnunt",
            "costume": "Combat Doctor",
            "character_image": "illust_inven_char100401_8.png",
            "skill_preview_image": "illust_skill_char100401_8.png",
            "standing": {
                "skeleton": "char100401.skel",
                "atlas": "char100401.atlas"
            },
            "cutscene": null,
            "dating": null
        },
        {
            "id": "100501",
            "character": "Wiggle",
            "costume": "Bomb Fanatic",
            "character_image": "illust_inven_char100501_9.png",
            "skill_preview_image": "illust_skill_char100501_9.png",
            "standing": {
                "skeleton": "char100501.skel",
                "atlas": "char100501.atlas"
            },
            "cutscene": {
                "skeleton": "cutscene_char100501.skel",
                "atlas": "cutscene_char100501.atlas"
            },
            "dating": null
        },
        {
            "id": "100502",
            "character": "Wiggle",
            "costume": "Bomb in the Hoodie",
            "character_image": "illust_inven_char100502_45.png",
            "skill_preview_image": "illust_skill_char100502_45.png",
            "standing": {
                "skeleton": "char100502.skel",
                "atlas": "char100502.atlas"
            },
            "cutscene": null,
            "dating": null
        },
        {
            "id": "100601",
            "character": "Lucrezia",
            "costume": "Seductive Wings",
            "character_image": "illust_inven_char100601_11.png",
            "skill_preview_image": "illust_skill_char100601_11.png",
            "standing": {
                "skeleton": "char100601.skel",
                "atlas": "char100601.atlas"
            },
            "cutscene": null,
            "dating": null
        },
        {
            "id": "100801",
            "character": "Bernie",
            "costume": "Righteous Raider Girl",
            "character_image": "illust_inven_char100801_12.png",
            "skill_preview_image": "illust_skill_char100801_12.png",
            "standing": {
                "skeleton": "char100801.skel",
                "atlas": "char100801.atlas"
            },
            "cutscene": null,
            "dating": null
        },
        {
            "id": "101101",
            "character": "Seir",
            "costume": "Demon's Daughter",
            "character_image": "illust_inven_char101101_67.png",
            "skill_preview_image": "illust_skill_char101101_67.png",
            "standing": {
                "skeleton": "char101101.skel",
                "atlas": "char101101.atlas"
            },
            "cutscene": {
                "skeleton": "cutscene_char101101.skel",
                "atlas": "cutscene_char101101.atlas"
            },
            "dating": null
        },
        {
            "id": "101102",
            "character": "Seir",
            "costume": "B-Rank Idol",
            "character_image": "illust_inven_char101102_25.png",
            "skill_preview_image": "illust_skill_char101102_25.png",
            "standing": {
                "skeleton": "char101102.skel",
                "atlas": "char101102.atlas"
            },
            "cutscene": {
                "skeleton": "cutscene_char101102.skel",
                "atlas": "cutscene_char101102.atlas"
            },
            "dating": null
        },
        {
            "id": "101103",
            "character": "Seir",
            "costume": "New Hire",
            "character_image": "illust_inven_char101103_150.png",
            "skill_preview_image": "illust_skill_char101103_150.png",
            "standing": {
                "skeleton": "char101103.skel",
                "atlas": "char101103.atlas"
            },
            "cutscene": {
                "skeleton": "cutscene_char101103.skel",
                "atlas": "cutscene_char101103.atlas"
            },
            "dating": null
        },
        {
            "id": "101201",
            "character": "Jayden",
            "costume": "Beautiful Gird Devotee",
            "character_image": "illust_inven_char101201_75.png",
            "skill_preview_image": "illust_skill_char101201_75.png",
            "standing": {
                "skeleton": "char101201.skel",
                "atlas": "char101201.atlas"
            },
            "cutscene": null,
            "dating": null
        },
        {
            "id": "101202",
            "character": "Jayden",
            "costume": "Manga Research Club",
            "character_image": "illust_inven_char101202_18.png",
            "skill_preview_image": "illust_skill_char101202_18.png",
            "standing": {
                "skeleton": "char101202.skel",
                "atlas": "char101202.atlas"
            },
            "cutscene": null,
            "dating": null
        },
        {
            "id": "101301",
            "character": "Emma",
            "costume": "Haggard Delinquent",
            "character_image": "illust_inven_char101301_61.png",
            "skill_preview_image": "illust_skill_char101301_61.png",
            "standing": {
                "skeleton": "char101301.skel",
                "atlas": "char101301.atlas"
            },
            "cutscene": null,
            "dating": null
        },
        {
            "id": "101302",
            "character": "Emma",
            "costume": "School Queen",
            "character_image": "illust_inven_char101302_19.png",
            "skill_preview_image": "illust_skill_char101302_19.png",
            "standing": {
                "skeleton": "char101302.skel",
                "atlas": "char101302.atlas"
            },
            "cutscene": null,
            "dating": null
        },
        {
            "id": "101401",
            "character": "Samay",
            "costume": "Kind Liberator",
            "character_image": "illust_inven_char101401_66.png",
            "skill_preview_image": "illust_skill_char101401_66.png",
            "standing": {
                "skeleton": "char101401.skel",
                "atlas": "char101401.atlas"
            },
            "cutscene": null,
            "dating": null
        },
        {
            "id": "101402",
            "character": "Samay",
            "costume": "Kind Student",
            "character_image": "illust_inven_char101402_16.png",
            "skill_preview_image": "illust_skill_char101402_16.png",
            "standing": {
                "skeleton": "char101402.skel",
                "atlas": "char101402.atlas"
            },
            "cutscene": null,
            "dating": null
        },
        {
            "id": "101501",
            "character": "Kry",
            "costume": "Liberated Marauder",
            "character_image": "illust_inven_char101501_65.png",
            "skill_preview_image": "illust_skill_char101501_65.png",
            "standing": {
                "skeleton": "char101501.skel",
                "atlas": "char101501.atlas"
            },
            "cutscene": null,
            "dating": null
        },
        {
            "id": "101502",
            "character": "Kry",
            "costume": "Violent Student",
            "character_image": "illust_inven_char101502_17.png",
            "skill_preview_image": "illust_skill_char101502_17.png",
            "standing": {
                "skeleton": "char101502.skel",
                "atlas": "char101502.atlas"
            },
            "cutscene": null,
            "dating": null
        },
        {
            "id": "101601",
            "character": "Celia",
            "costume": "The Curse",
            "character_image": "illust_inven_char101601_78.png",
            "skill_preview_image": "illust_skill_char101601_78.png",
            "standing": {
                "skeleton": "char101601.skel",
                "atlas": "char101601.atlas"
            },
            "cutscene": null,
            "dating": null
        },
        {
            "id": "103201",
            "character": "Carlson",
            "costume": "The Mercenary Knight",
            "character_image": "illust_inven_char103201_31.png",
            "skill_preview_image": "illust_skill_char103201_31.png",
            "standing": {
                "skeleton": "char103201.skel",
                "atlas": "char103201.atlas"
            },
            "cutscene": {
                "skeleton": "cutscene_char103201.skel",
                "atlas": "cutscene_char103201.atlas"
            },
            "dating": null
        },
        {
            "id": "103301",
            "character": "Lydia",
            "costume": "Apprentice Spearman",
            "character_image": "illust_inven_char103301_32.png",
            "skill_preview_image": "illust_skill_char103301_32.png",
            "standing": {
                "skeleton": "char103301.skel",
                "atlas": "char103301.atlas"
            },
            "cutscene": {
                "skeleton": "cutscene_char103301.skel",
                "atlas": "cutscene_char103301.atlas"
            },
            "dating": null
        },
        {
            "id": "103401",
            "character": "Rigenette",
            "costume": "Little Hunter",
            "character_image": "illust_inven_char103401_33.png",
            "skill_preview_image": "illust_skill_char103401_33.png",
            "standing": {
                "skeleton": "char103401.skel",
                "atlas": "char103401.atlas"
            },
            "cutscene": {
                "skeleton": "cutscene_char103401.skel",
                "atlas": "cutscene_char103401.atlas"
            },
            "dating": null
        },
        {
            "id": "103501",
            "character": "Beatrice",
            "costume": "The Mighty Warrior of the Tribe",
            "character_image": "illust_inven_char103501_34.png",
            "skill_preview_image": "illust_skill_char103501_34.png",
            "standing": {
                "skeleton": "char103501.skel",
                "atlas": "char103501.atlas"
            },
            "cutscene": {
                "skeleton": "cutscene_char103501.skel",
                "atlas": "cutscene_char103501.atlas"
            },
            "dating": null
        },
        {
            "id": "103601",
            "character": "Maria",
            "costume": "Archmage",
            "character_image": "illust_inven_char103601_35.png",
            "skill_preview_image": "illust_skill_char103601_35.png",
            "standing": {
                "skeleton": "char103601.skel",
                "atlas": "char103601.atlas"
            },
            "cutscene": null,
            "dating": null
        },
        {
            "id": "103701",
            "character": "Arines",
            "costume": "Priest of Vitality",
            "character_image": "illust_inven_char103701_36.png",
            "skill_preview_image": "illust_skill_char103701_36.png",
            "standing": {
                "skeleton": "char103701.skel",
                "atlas": "char103701.atlas"
            },
            "cutscene": null,
            "dating": null
        },
        {
            "id": "003601",
            "character": "Olivier",
            "costume": "White Witch",
            "character_image": "illust_inven_char003601_138.png",
            "skill_preview_image": "illust_skill_char003601_138.png",
            "standing": {
                "skeleton": "char003601.skel",
                "atlas": "char003601.atlas"
            },
            "cutscene": null,
            "dating": null
        }
    ],
    "dating": {
        "1": "003303",
        "2": "003402",
        "3": "003203",
        "4": "001106",
        "5": "060802",
        "6": "067603",
        "7": "000296"
    }
}
